{
  "db_name": "PostgreSQL",
  "query": "SELECT id, hash, author, episode, introduce, time, title, url FROM rebase_daily WHERE id = $1",
  "describe": {
    "columns": [
      {
        "ordinal": 0,
        "name": "id",
        "type_info": "Int4"
      },
      {
        "ordinal": 1,
        "name": "hash",
        "type_info": "Text"
      },
      {
        "ordinal": 2,
        "name": "author",
        "type_info": "Text"
      },
      {
        "ordinal": 3,
        "name": "episode",
        "type_info": "Text"
      },
      {
        "ordinal": 4,
        "name": "introduce",
        "type_info": "Text"
      },
      {
        "ordinal": 5,
        "name": "time",
        "type_info": "Timestamptz"
      },
      {
        "ordinal": 6,
        "name": "title",
        "type_info": "Text"
      },
      {
        "ordinal": 7,
        "name": "url",
        "type_info": "Text"
      }
    ],
    "parameters": {
      "Left": [
        "Int4"
      ]
    },
    "nullable": [
      false,
      false,
      false,
      false,
      false,
      false,
      false,
      false
    ]
  },
  "hash": "9da84023e7fffd86eaa205a71d9f8aa55e810e6e396f2c35471bb20741552f9f"
}
